autopandas/__init__.py
autopandas/autopandas.py
autopandas/data/__init__.py
autopandas/data/adult.csv
autopandas/data/boston_test.csv
autopandas/data/boston_train.csv
autopandas/data/datasets.py
autopandas/data/diabetes.csv
autopandas/data/iris.csv
autopandas/data/mushrooms.csv
autopandas/data/seeds.csv
autopandas/data/squares1.csv
autopandas/data/squares2.csv
autopandas/data/titanic_test.csv
autopandas/data/titanic_train.csv
autopandas/data/wine.csv
autopandas/data/__pycache__/__init__.cpython-37.pyc
autopandas/data/__pycache__/datasets.cpython-37.pyc
autopandas/generators/__init__.py
autopandas/generators/anm.py
autopandas/generators/artificial.py
autopandas/generators/autoencoder.py
autopandas/generators/copula.py
autopandas/generators/copycat.py
autopandas/generators/fae.py
autopandas/generators/generators.py
autopandas/generators/gmm.py
autopandas/generators/kde.py
autopandas/generators/sae.py
autopandas/generators/vae.py
autopandas/utils/__init__.py
autopandas/utils/automl.py
autopandas/utils/benchmark.py
autopandas/utils/datasets.py
autopandas/utils/encoding.py
autopandas/utils/imputation.py
autopandas/utils/mdlp.py
autopandas/utils/metric.py
autopandas/utils/nn_adversarial_accuracy.py
autopandas/utils/nnaa.py
autopandas/utils/normalization.py
autopandas/utils/reduction.py
autopandas/utils/sdv.py
autopandas/utils/sdv_converter.py
autopandas/utils/utilities.py
autopandas/utils/visualization.py
autopandas-0.5.1.dist-info/METADATA
autopandas-0.5.1.dist-info/WHEEL
autopandas-0.5.1.dist-info/top_level.txt
autopandas-0.5.1.dist-info/RECORD
