Metadata-Version: 2.1
Name: autopandas
Version: 0.5.1
Summary: Process, visualize and use data easily.
Home-page: https://github.com/didayolo/autopandas
Author: Adrien Pavao
Author-email: adrien.pavao@gmail.com
License: UNKNOWN
Platform: UNKNOWN
Classifier: Programming Language :: Python :: 3
Classifier: Operating System :: Unix
